filterframes/__init__.py
filterframes/filterframes.py
filterframes-0.1.3.dist-info/LICENSE
filterframes-0.1.3.dist-info/METADATA
filterframes-0.1.3.dist-info/WHEEL
filterframes-0.1.3.dist-info/top_level.txt
filterframes-0.1.3.dist-info/RECORD
