Metadata-Version: 2.1
Name: filterframes
Version: 0.1.3
Summary: A very simple DTASelect-Filter.txt parser.
Author-email: Patrick Garrett <pgarrett@scripps.edu>
License: MIT License
Project-URL: repository, https://github.com/pgarrett-scripps/FilterFrames.git
Keywords: IP2,PASER,Parser,Streamlit,DTASelect-filter,Peptide,Protein,Proteomics
Classifier: Programming Language :: Python :: 3
Classifier: Development Status :: 4 - Beta
Classifier: License :: OSI Approved :: MIT License
Classifier: Operating System :: OS Independent
Requires-Python: >=3.8
License-File: LICENSE
Requires-Dist: pandas
